Pryme/__init__.py
Pryme/prymepackage.py
PrymePython-0.0.12.dist-info/LICENSE
PrymePython-0.0.12.dist-info/METADATA
PrymePython-0.0.12.dist-info/WHEEL
PrymePython-0.0.12.dist-info/top_level.txt
PrymePython-0.0.12.dist-info/RECORD
